MANIFEST.in
README.rst
setup.py
blanc_basic_events/__init__.py
blanc_basic_events/admin.py
blanc_basic_events/apps.py
blanc_basic_events/forms.py
blanc_basic_events/models.py
blanc_basic_events/tests.py
blanc_basic_events/urls.py
blanc_basic_events/views.py
blanc_basic_events.egg-info/PKG-INFO
blanc_basic_events.egg-info/SOURCES.txt
blanc_basic_events.egg-info/dependency_links.txt
blanc_basic_events.egg-info/requires.txt
blanc_basic_events.egg-info/top_level.txt
blanc_basic_events/migrations/0001_initial.py
blanc_basic_events/migrations/__init__.py
blanc_basic_events/templatetags/__init__.py
blanc_basic_events/templatetags/events_tags.py